EventHub_Listeners/Listener.py
EventHub_Listeners/__init__.py
EventListeners-0.1.2.dist-info/METADATA
EventListeners-0.1.2.dist-info/WHEEL
EventListeners-0.1.2.dist-info/top_level.txt
EventListeners-0.1.2.dist-info/RECORD
