Metadata-Version: 2.1
Name: EventListeners
Version: 0.1.2
Summary: Event hub listener for Common Spec use case that triggers DBX jobs
Author: Archana Bellamkonda
Author-email: archana.bellamkonda@lamresearch.com
Requires-Dist: azure-eventhub
Requires-Dist: azure-keyvault
Requires-Dist: azure-identity
Requires-Dist: requests
